.bowerrc
LICENSE
MANIFEST.in
README.md
README.rst
bower.json
package.json
setup.json
setup.py
mermaid/__init__.py
mermaid/static/nb-mermaid/.git
mermaid/static/nb-mermaid/index.html
mermaid/static/nb-mermaid/init.js
mermaid/static/nb-mermaid/nb-mermaid.css
mermaid/static/nb-mermaid/nb-mermaid.js
mermaid/static/nb-mermaid/lib/mermaid/.bower.json
mermaid/static/nb-mermaid/lib/mermaid/bower.json
mermaid/static/nb-mermaid/lib/mermaid/dist/mermaid.css
mermaid/static/nb-mermaid/lib/mermaid/dist/mermaid.forest.css
mermaid/static/nb-mermaid/lib/mermaid/dist/mermaid.min.js
nb_mermaid.egg-info/PKG-INFO
nb_mermaid.egg-info/SOURCES.txt
nb_mermaid.egg-info/dependency_links.txt
nb_mermaid.egg-info/requires.txt
nb_mermaid.egg-info/top_level.txt