Metadata-Version: 1.1
Name: nb-mermaid
Version: 0.1.0
Summary: Mermaid diagrams in the IPython Notebook
Home-page: http://github.com/bollwyvl/nb-mermaid
Author: Nicholas Bollweg
Author-email: nick.bollweg@gmail.com
License: BSD
Keywords: IPython mermaid diagram
Platform: UNKNOWN
Classifier: Framework :: IPython
Classifier: Natural Language :: English
Classifier: Programming Language :: Python
Classifier: Intended Audience :: Developers
Classifier: Development Status :: 3 - Alpha
Classifier: Operating System :: OS Independent
Classifier: Programming Language :: Python :: 3
Classifier: Programming Language :: Python :: 2
Classifier: License :: OSI Approved :: BSD License
Classifier: Topic :: Scientific/Engineering :: Human Machine Interfaces
Classifier: Topic :: Scientific/Engineering :: Visualization
